MANIFEST.in
README.md
requirements.txt
setup.cfg
setup.py
python_ups.egg-info/PKG-INFO
python_ups.egg-info/SOURCES.txt
python_ups.egg-info/dependency_links.txt
python_ups.egg-info/requires.txt
python_ups.egg-info/top_level.txt
ups/__init__.py
ups/client.py
ups/model.py
ups/wsdl/Error1.1.xsd
ups/wsdl/RateWS.wsdl
ups/wsdl/RateWebServiceSchema.xsd
ups/wsdl/UPSSecurity.xsd
ups/wsdl/common.xsd