Metadata-Version: 1.0
Name: python-ups
Version: 0.0.3
Summary: UPS shipping interface
Home-page: http://github.com/marcelnicolay/python-ups
Author: Marcel Nicolay
Author-email: marcel.nicolay@gmail.com
License: OSI
Keywords: ups,shipping
Platform: UNKNOWN
